[
  {
    "id": "03b7cbd7",
    "source": "extension",
    "book": "22bet",
    "sport": null,
    "league": null,
    "market": "Prop",
    "participant": "Unknown participant",
    "side": "other",
    "line": 0.0,
    "odds_american": 0,
    "ev_pct": 0.0,
    "hit_prob_pct": 51.5,
    "fair_odds_american": null,
    "url": null,
    "captured_at": "2026-03-24T20:14:46.083000Z"
  },
  {
    "id": "cca3ec9f",
    "source": "extension",
    "book": "PointsBet (Australia)",
    "sport": null,
    "league": null,
    "market": "Prop",
    "participant": "Unknown participant",
    "side": "other",
    "line": 0.0,
    "odds_american": 0,
    "ev_pct": 0.0,
    "hit_prob_pct": 47.9,
    "fair_odds_american": null,
    "url": null,
    "captured_at": "2026-03-24T20:14:46.083000Z"
  },
  {
    "id": "04a2f56a",
    "source": "extension",
    "book": "1XBet",
    "sport": null,
    "league": null,
    "market": "Prop",
    "participant": "Unknown participant",
    "side": "other",
    "line": 0.0,
    "odds_american": 0,
    "ev_pct": 0.0,
    "hit_prob_pct": 54.2,
    "fair_odds_american": null,
    "url": null,
    "captured_at": "2026-03-24T20:14:46.083000Z"
  },
  {
    "id": "411454e5",
    "source": "extension",
    "book": "NorthStar Bets",
    "sport": null,
    "league": null,
    "market": "Prop",
    "participant": "Unknown participant",
    "side": "other",
    "line": 0.0,
    "odds_american": 0,
    "ev_pct": 0.0,
    "hit_prob_pct": 47.6,
    "fair_odds_american": null,
    "url": null,
    "captured_at": "2026-03-24T20:14:46.084000Z"
  },
  {
    "id": "bc5374b2",
    "source": "extension",
    "book": "CampoBet",
    "sport": null,
    "league": null,
    "market": "Prop",
    "participant": "Unknown participant",
    "side": "other",
    "line": 0.0,
    "odds_american": 0,
    "ev_pct": 0.0,
    "hit_prob_pct": 43.3,
    "fair_odds_american": null,
    "url": null,
    "captured_at": "2026-03-24T20:14:46.084000Z"
  },
  {
    "id": "574d3151",
    "source": "extension",
    "book": "Betfair",
    "sport": null,
    "league": null,
    "market": "Prop",
    "participant": "Unknown participant",
    "side": "other",
    "line": 0.0,
    "odds_american": 0,
    "ev_pct": 0.0,
    "hit_prob_pct": 50.2,
    "fair_odds_american": null,
    "url": null,
    "captured_at": "2026-03-24T20:14:46.084000Z"
  },
  {
    "id": "917e236b",
    "source": "extension",
    "book": "Novig",
    "sport": null,
    "league": null,
    "market": "Prop",
    "participant": "Unknown participant",
    "side": "other",
    "line": 0.0,
    "odds_american": 0,
    "ev_pct": 0.0,
    "hit_prob_pct": 49.0,
    "fair_odds_american": null,
    "url": null,
    "captured_at": "2026-03-24T20:14:46.084000Z"
  },
  {
    "id": "8f319a25",
    "source": "extension",
    "book": "Bally Bet",
    "sport": null,
    "league": null,
    "market": "Prop",
    "participant": "Unknown participant",
    "side": "other",
    "line": 0.0,
    "odds_american": 0,
    "ev_pct": 0.0,
    "hit_prob_pct": 58.1,
    "fair_odds_american": null,
    "url": null,
    "captured_at": "2026-03-24T20:14:46.084000Z"
  },
  {
    "id": "ed3e9d07",
    "source": "extension",
    "book": "Hard Rock",
    "sport": null,
    "league": null,
    "market": "Prop",
    "participant": "Unknown participant",
    "side": "other",
    "line": 0.0,
    "odds_american": 0,
    "ev_pct": 0.0,
    "hit_prob_pct": 60.0,
    "fair_odds_american": null,
    "url": null,
    "captured_at": "2026-03-24T20:14:46.084000Z"
  },
  {
    "id": "516beab0",
    "source": "extension",
    "book": "BetRivers",
    "sport": null,
    "league": null,
    "market": "Prop",
    "participant": "Unknown participant",
    "side": "other",
    "line": 0.0,
    "odds_american": 0,
    "ev_pct": 0.0,
    "hit_prob_pct": 48.4,
    "fair_odds_american": null,
    "url": null,
    "captured_at": "2026-03-24T20:14:46.084000Z"
  },
  {
    "id": "66fa4f54",
    "source": "extension",
    "book": "STN Sports",
    "sport": null,
    "league": null,
    "market": "Prop",
    "participant": "Unknown participant",
    "side": "other",
    "line": 0.0,
    "odds_american": 0,
    "ev_pct": 0.0,
    "hit_prob_pct": 54.5,
    "fair_odds_american": null,
    "url": null,
    "captured_at": "2026-03-24T20:14:46.084000Z"
  },
  {
    "id": "d3678187",
    "source": "extension",
    "book": "Pinnacle",
    "sport": null,
    "league": null,
    "market": "Prop",
    "participant": "Unknown participant",
    "side": "other",
    "line": 0.0,
    "odds_american": 0,
    "ev_pct": 0.0,
    "hit_prob_pct": 46.4,
    "fair_odds_american": null,
    "url": null,
    "captured_at": "2026-03-24T20:14:46.084000Z"
  },
  {
    "id": "bb36036d",
    "source": "extension",
    "book": "Betsafe",
    "sport": null,
    "league": null,
    "market": "Prop",
    "participant": "Unknown participant",
    "side": "other",
    "line": 0.0,
    "odds_american": 0,
    "ev_pct": 0.0,
    "hit_prob_pct": 51.2,
    "fair_odds_american": null,
    "url": null,
    "captured_at": "2026-03-24T20:14:46.084000Z"
  },
  {
    "id": "403e93e8",
    "source": "extension",
    "book": "BetMGM",
    "sport": null,
    "league": null,
    "market": "Prop",
    "participant": "Unknown participant",
    "side": "other",
    "line": 0.0,
    "odds_american": 0,
    "ev_pct": 0.0,
    "hit_prob_pct": 72.4,
    "fair_odds_american": null,
    "url": null,
    "captured_at": "2026-03-24T20:14:46.084000Z"
  },
  {
    "id": "b2e2da18",
    "source": "extension",
    "book": "Polymarket",
    "sport": null,
    "league": null,
    "market": "Prop",
    "participant": "Unknown participant",
    "side": "other",
    "line": 0.0,
    "odds_american": 0,
    "ev_pct": 0.0,
    "hit_prob_pct": 47.5,
    "fair_odds_american": null,
    "url": null,
    "captured_at": "2026-03-24T20:14:46.085000Z"
  },
  {
    "id": "76d711ed",
    "source": "extension",
    "book": "4Cx",
    "sport": null,
    "league": null,
    "market": "Prop",
    "participant": "Unknown participant",
    "side": "other",
    "line": 0.0,
    "odds_american": 0,
    "ev_pct": 0.0,
    "hit_prob_pct": 56.5,
    "fair_odds_american": null,
    "url": null,
    "captured_at": "2026-03-24T20:14:46.085000Z"
  },
  {
    "id": "ecdbdd36",
    "source": "extension",
    "book": "betr (Australia)",
    "sport": null,
    "league": null,
    "market": "Prop",
    "participant": "Unknown participant",
    "side": "other",
    "line": 0.0,
    "odds_american": 0,
    "ev_pct": 0.0,
    "hit_prob_pct": 47.7,
    "fair_odds_american": null,
    "url": null,
    "captured_at": "2026-03-24T20:14:46.085000Z"
  },
  {
    "id": "eed0750d",
    "source": "extension",
    "book": "Prophet X",
    "sport": null,
    "league": null,
    "market": "Prop",
    "participant": "Unknown participant",
    "side": "other",
    "line": 0.0,
    "odds_american": 0,
    "ev_pct": 0.0,
    "hit_prob_pct": 49.2,
    "fair_odds_american": null,
    "url": null,
    "captured_at": "2026-03-24T20:14:46.085000Z"
  },
  {
    "id": "d386c7c6",
    "source": "extension",
    "book": "Play Alberta",
    "sport": null,
    "league": null,
    "market": "Prop",
    "participant": "Unknown participant",
    "side": "other",
    "line": 0.0,
    "odds_american": 0,
    "ev_pct": 0.0,
    "hit_prob_pct": 54.0,
    "fair_odds_american": null,
    "url": null,
    "captured_at": "2026-03-24T20:14:46.085000Z"
  },
  {
    "id": "aa78bc08",
    "source": "extension",
    "book": "Betano",
    "sport": null,
    "league": null,
    "market": "Prop",
    "participant": "Unknown participant",
    "side": "other",
    "line": 0.0,
    "odds_american": 0,
    "ev_pct": 0.0,
    "hit_prob_pct": 53.5,
    "fair_odds_american": null,
    "url": null,
    "captured_at": "2026-03-24T20:14:46.085000Z"
  },
  {
    "id": "043afcea",
    "source": "extension",
    "book": "theScore",
    "sport": null,
    "league": null,
    "market": "Prop",
    "participant": "Unknown participant",
    "side": "other",
    "line": 0.0,
    "odds_american": 0,
    "ev_pct": 0.0,
    "hit_prob_pct": 58.6,
    "fair_odds_american": null,
    "url": null,
    "captured_at": "2026-03-24T20:14:46.085000Z"
  },
  {
    "id": "640849b6",
    "source": "extension",
    "book": "Sporttrade",
    "sport": null,
    "league": null,
    "market": "Prop",
    "participant": "Unknown participant",
    "side": "other",
    "line": 0.0,
    "odds_american": 0,
    "ev_pct": 0.0,
    "hit_prob_pct": 40.2,
    "fair_odds_american": null,
    "url": null,
    "captured_at": "2026-03-24T20:14:46.086000Z"
  },
  {
    "id": "535371f4",
    "source": "extension",
    "book": "Boomers",
    "sport": null,
    "league": null,
    "market": "Prop",
    "participant": "Unknown participant",
    "side": "other",
    "line": 0.0,
    "odds_american": 0,
    "ev_pct": 0.0,
    "hit_prob_pct": 66.0,
    "fair_odds_american": null,
    "url": null,
    "captured_at": "2026-03-24T20:14:46.086000Z"
  },
  {
    "id": "5fc0b844",
    "source": "extension",
    "book": "BetOpenly",
    "sport": null,
    "league": null,
    "market": "Prop",
    "participant": "Unknown participant",
    "side": "other",
    "line": 0.0,
    "odds_american": 0,
    "ev_pct": 0.0,
    "hit_prob_pct": 51.2,
    "fair_odds_american": null,
    "url": null,
    "captured_at": "2026-03-24T20:14:46.087000Z"
  },
  {
    "id": "387f35f8",
    "source": "extension",
    "book": "betJACK",
    "sport": null,
    "league": null,
    "market": "Prop",
    "participant": "Unknown participant",
    "side": "other",
    "line": 0.0,
    "odds_american": 0,
    "ev_pct": 0.0,
    "hit_prob_pct": 53.3,
    "fair_odds_american": null,
    "url": null,
    "captured_at": "2026-03-24T20:14:46.087000Z"
  },
  {
    "id": "56d12c5c",
    "source": "extension",
    "book": "888sport",
    "sport": null,
    "league": null,
    "market": "Prop",
    "participant": "Unknown participant",
    "side": "other",
    "line": 0.0,
    "odds_american": 0,
    "ev_pct": 0.0,
    "hit_prob_pct": 48.2,
    "fair_odds_american": null,
    "url": null,
    "captured_at": "2026-03-24T20:14:46.087000Z"
  },
  {
    "id": "ca60b582",
    "source": "extension",
    "book": "Ladbrokes (Australia)",
    "sport": null,
    "league": null,
    "market": "Prop",
    "participant": "Unknown participant",
    "side": "other",
    "line": 0.0,
    "odds_american": 0,
    "ev_pct": 0.0,
    "hit_prob_pct": 57.8,
    "fair_odds_american": null,
    "url": null,
    "captured_at": "2026-03-24T20:14:46.087000Z"
  },
  {
    "id": "d8d61248",
    "source": "extension",
    "book": "Fanatics",
    "sport": null,
    "league": null,
    "market": "Prop",
    "participant": "Unknown participant",
    "side": "other",
    "line": 0.0,
    "odds_american": 0,
    "ev_pct": 0.0,
    "hit_prob_pct": 62.3,
    "fair_odds_american": null,
    "url": null,
    "captured_at": "2026-03-24T20:14:46.087000Z"
  },
  {
    "id": "ca15f09f",
    "source": "extension",
    "book": "Coolbet",
    "sport": null,
    "league": null,
    "market": "Prop",
    "participant": "Unknown participant",
    "side": "other",
    "line": 0.0,
    "odds_american": 0,
    "ev_pct": 0.0,
    "hit_prob_pct": 64.1,
    "fair_odds_american": null,
    "url": null,
    "captured_at": "2026-03-24T20:14:46.087000Z"
  },
  {
    "id": "734eb23a",
    "source": "extension",
    "book": "Bodog",
    "sport": null,
    "league": null,
    "market": "Prop",
    "participant": "Unknown participant",
    "side": "other",
    "line": 0.0,
    "odds_american": 0,
    "ev_pct": 0.0,
    "hit_prob_pct": 43.0,
    "fair_odds_american": null,
    "url": null,
    "captured_at": "2026-03-24T20:14:46.087000Z"
  },
  {
    "id": "b0dee7fd",
    "source": "extension",
    "book": "Mise-o-jeu",
    "sport": null,
    "league": null,
    "market": "Prop",
    "participant": "Unknown participant",
    "side": "other",
    "line": 0.0,
    "odds_american": 0,
    "ev_pct": 0.0,
    "hit_prob_pct": 53.0,
    "fair_odds_american": null,
    "url": null,
    "captured_at": "2026-03-24T20:14:46.087000Z"
  },
  {
    "id": "d3d8d356",
    "source": "extension",
    "book": "Coral",
    "sport": null,
    "league": null,
    "market": "Prop",
    "participant": "Unknown participant",
    "side": "other",
    "line": 0.0,
    "odds_american": 0,
    "ev_pct": 0.0,
    "hit_prob_pct": 63.2,
    "fair_odds_american": null,
    "url": null,
    "captured_at": "2026-03-24T20:14:46.087000Z"
  },
  {
    "id": "50a2090c",
    "source": "extension",
    "book": "Dafabet",
    "sport": null,
    "league": null,
    "market": "Prop",
    "participant": "Unknown participant",
    "side": "other",
    "line": 0.0,
    "odds_american": 0,
    "ev_pct": 0.0,
    "hit_prob_pct": 50.0,
    "fair_odds_american": null,
    "url": null,
    "captured_at": "2026-03-24T20:14:46.088000Z"
  },
  {
    "id": "0ef9fa12",
    "source": "extension",
    "book": "Caesars",
    "sport": null,
    "league": null,
    "market": "Prop",
    "participant": "Unknown participant",
    "side": "other",
    "line": 0.0,
    "odds_american": 0,
    "ev_pct": 0.0,
    "hit_prob_pct": 38.0,
    "fair_odds_american": null,
    "url": null,
    "captured_at": "2026-03-24T20:14:46.088000Z"
  },
  {
    "id": "a5a7965f",
    "source": "extension",
    "book": "Superbet",
    "sport": null,
    "league": null,
    "market": "Prop",
    "participant": "Unknown participant",
    "side": "other",
    "line": 0.0,
    "odds_american": 0,
    "ev_pct": 0.0,
    "hit_prob_pct": 65.9,
    "fair_odds_american": null,
    "url": null,
    "captured_at": "2026-03-24T20:14:46.088000Z"
  },
  {
    "id": "1c7812b0",
    "source": "extension",
    "book": "Desert Diamond",
    "sport": null,
    "league": null,
    "market": "Prop",
    "participant": "Unknown participant",
    "side": "other",
    "line": 0.0,
    "odds_american": 0,
    "ev_pct": 0.0,
    "hit_prob_pct": 58.6,
    "fair_odds_american": null,
    "url": null,
    "captured_at": "2026-03-24T20:14:46.088000Z"
  }
]