[
  {
    "id": "6af5e606",
    "source": "unknown",
    "book": "D",
    "sport": null,
    "league": null,
    "market": "Points",
    "participant": "A",
    "side": "over",
    "line": null,
    "odds_american": -110,
    "ev_pct": null,
    "hit_prob_pct": 50.0,
    "fair_odds_american": null,
    "url": null,
    "captured_at": "2026-04-02T22:53:36.296057Z"
  },
  {
    "id": "7b8097d0",
    "source": "unknown",
    "book": "F",
    "sport": null,
    "league": null,
    "market": "Moneyline",
    "participant": "B",
    "side": "home",
    "line": null,
    "odds_american": 120,
    "ev_pct": null,
    "hit_prob_pct": 45.0,
    "fair_odds_american": null,
    "url": null,
    "captured_at": "2026-04-02T22:53:36.296086Z"
  }
]